Metadata-Version: 2.1
Name: django-plugin-database-url
Version: 0.1
Summary: Django plugin that reads the DATABASE_URL environment variable
Author: Simon Willison
License: Apache-2.0
Project-URL: Homepage, https://github.com/simonw/django-plugin-database-url
Project-URL: Changelog, https://github.com/simonw/django-plugin-database-url/releases
Project-URL: Issues, https://github.com/simonw/django-plugin-database-url/issues
Project-URL: CI, https://github.com/simonw/django-plugin-database-url/actions
Classifier: License :: OSI Approved :: Apache Software License
License-File: LICENSE
Requires-Dist: django
Requires-Dist: djp
Requires-Dist: dj-database-url
Provides-Extra: test
Requires-Dist: pytest ; extra == 'test'
Requires-Dist: pytest-django ; extra == 'test'
Requires-Dist: pytest-env ; extra == 'test'
